guacamole_compose/VERSION
guacamole_compose/__init__.py
guacamole_compose/arguments.yaml
guacamole_compose/cli.py
guacamole_compose/templates/docker-compose.yml.haproxy.template
guacamole_compose/templates/docker-compose.yml.template
guacamole_compose/templates/favicon.ico
guacamole_compose/templates/guacamole-auth-ldap-1.3.0.jar
guacamole_compose/templates/guacamole-auth-radius-1.3.0.jar
guacamole_compose/templates/guacamole.properties.template
guacamole_compose/templates/haproxy.template
guacamole_compose/templates/haproxy_init.cfg
guacamole_compose/templates/initdb.sh.template
guacamole_compose/templates/initdb.sql.script
guacamole_compose/templates/nginx_conf.template
guacamole_compose/templates/nginx_init.conf
guacamole_compose/templates/parameters.yaml
guacamole_compose/templates/server.xml
guacamole_compose-0.1.7.dist-info/LICENSE
guacamole_compose-0.1.7.dist-info/METADATA
guacamole_compose-0.1.7.dist-info/WHEEL
guacamole_compose-0.1.7.dist-info/entry_points.txt
guacamole_compose-0.1.7.dist-info/top_level.txt
guacamole_compose-0.1.7.dist-info/RECORD
