Metadata-Version: 2.1
Name: guacamole-compose
Version: 0.1.7
Summary: Easy deployment of Apache Guacamole.
Home-page: https://github.com/alphabet5/guacamole-compose
Author: John Burt
Author-email: johnburt.jab@gmail.com
License: UNKNOWN
Platform: UNKNOWN
Classifier: Programming Language :: Python :: 3
Classifier: License :: OSI Approved :: Apache Software License
Classifier: Operating System :: OS Independent
Requires-Python: >=3.8
Requires-Dist: ldap3 (>=2.9)
Requires-Dist: pymysql (>=1.0.2)
Requires-Dist: docker (>=5.0.0)
Requires-Dist: sqlalchemy (>=1.4.11)
Requires-Dist: yamlarg (>=0.0.6)
Requires-Dist: pyyaml (>=5.4.1)
Requires-Dist: cryptography (>=3.4.7)
Requires-Dist: cffi (>=1.14.5)
Requires-Dist: dnspython (>=2.1.0)
Requires-Dist: docker-compose (>=1.29.2)
